LightAgent/__init__.py
LightAgent/la_core.py
lightagent-0.1.7.dist-info/LICENSE
lightagent-0.1.7.dist-info/METADATA
lightagent-0.1.7.dist-info/WHEEL
lightagent-0.1.7.dist-info/entry_points.txt
lightagent-0.1.7.dist-info/RECORD
