Metadata-Version: 2.1
Name: LightAgent
Version: 0.1.7
Summary: A lightweight agent for Python
Home-page: https://github.com/wxai-space/LightAgent
License: Apache 2.0
Author: caiweige
Author-email: caiweige@qq.com
Requires-Python: >=3.10,<3.12
Classifier: License :: Other/Proprietary License
Classifier: Programming Language :: Python :: 3
Classifier: Programming Language :: Python :: 3.10
Classifier: Programming Language :: Python :: 3.11
Requires-Dist: colorama (==0.4.6)
Requires-Dist: httpx (==0.28.1)
Requires-Dist: loguru (==0.7.3)
Requires-Dist: openai (==1.59.3)
Requires-Dist: requests (==2.32.3)
Project-URL: Repository, https://github.com/wxai-space/LightAgent
